multiformats_config/__init__.py
multiformats_config/config.py
multiformats_config/multibase-table.json
multiformats_config/multibase.py
multiformats_config/multicodec-table.json
multiformats_config/multicodec.py
multiformats_config/py.typed
makkus.multiformats_config-0.2.2.dist-info/LICENSE
makkus.multiformats_config-0.2.2.dist-info/METADATA
makkus.multiformats_config-0.2.2.dist-info/WHEEL
makkus.multiformats_config-0.2.2.dist-info/top_level.txt
makkus.multiformats_config-0.2.2.dist-info/RECORD
